{
  "members": [
    {
      "id": "MEM-2023-001",
      "firstName": "Yoooooowww",
      "middleName": "David",
      "lastName": "Smith",
      "nameExtensions": "Jr.",
      "status": "Active",
      "birthDate": "2002-05-15T00:00:00.000Z",
      "profession": "Software Engineer",
      "email": "john.smith@example.com",
      "contact": "+1 (555) 123-4567",
      "address": "123 Main Street, Anytown, USA 12345",
      "dateJoined": "2023-01-15T00:00:00.000Z",
      "position": "Member",
      "contribution": "$500",
      "absences": "2"
    },
    {
      "id": "MEM-2023-002",
      "firstName": "Betty",
      "middleName": "Ann",
      "lastName": "Smith",
      "nameExtensions": "",
      "status": "Active",
      "birthDate": "1998-02-10T00:00:00.000Z",
      "profession": "UI/UX Designer",
      "email": "betty.smith@example.com",
      "contact": "+1 (555) 987-6543",
      "address": "456 Oak Avenue, Somewhere, USA 67890",
      "dateJoined": "2023-03-20T00:00:00.000Z",
      "position": "Member",
      "contribution": "$450",
      "absences": "1"
    },
    {
      "id": "MEM-2023-003",
      "firstName": "Mary",
      "middleName": "Jane",
      "lastName": "Wilson",
      "nameExtensions": "",
      "status": "Active",
      "birthDate": "1990-11-22T00:00:00.000Z",
      "profession": "Project Manager",
      "email": "mary.wilson@example.com",
      "contact": "+1 (555) 234-5678",
      "address": "789 Pine Street, Elsewhere, USA 13579",
      "dateJoined": "2023-02-05T00:00:00.000Z",
      "position": "Committee Head",
      "contribution": "$600",
      "absences": "0"
    }
  ],

  "event": [
    {
      "id": "EVT-2023-001",
      "imageUrl": "https://images.pexels.com/photos/9543740/pexels-photo-9543740.jpeg?auto=compress&cs=tinysrgb&w=1260&h=750&dpr=2",
      "name": "Community Clean-up",
      "date": "2025-05-15",
      "starttime": "10:00 AM",
      "endtime": "12:00 PM",
      "attendanceCode": "CC2023",
      "attended": "Attended",
      "happeningNow": true,
      "participants": [
        {
          "id": "MEM-2023-001",
          "name": "Yoooooowww David Smith Jr.",
          "feedback": "Great event!"
        },
        {
          "id": "MEM-2023-002",
          "name": "Betty Ann Smith",
          "feedback": "Very informative."
        }
      ]
    },
    {
      "id": "EVT-2023-002",
      "imageUrl": "https://images.pexels.com/photos/6646855/pexels-photo-6646855.jpeg?auto=compress&cs=tinysrgb&w=1260&h=750&dpr=2",
      "name": "Charity Run",
      "date": "2025-05-20",
      "starttime": "08:00 AM",
      "endtime": "10:00 AM",
      "attendanceCode": "CR2023",
      "attended": "Missed",
      "happeningNow": false,
      "participants": [
        {
          "id": "MEM-2023-001",
          "name": "Yoooooowww David Smith Jr.",
          "feedback": "Had a great time!"
        },
        {
          "id": "MEM-2023-003",
          "name": "Mary Jane Wilson",
          "feedback": "Great experience!"
        }
      ]
    },
    {
      "id": "EVT-2023-003",
      "imageUrl": "https://images.pexels.com/photos/1181622/pexels-photo-1181622.jpeg?auto=compress&cs=tinysrgb&w=1260&h=750&dpr=2",
      "name": "Tech Meetup",
      "date": "2025-05-25",
      "starttime": "6:30 PM",
      "endtime": "8:30 PM",
      "attended": "N/A",
      "attendanceCode": "TM2023",
      "happeningNow": true,
      "participants": [
        {
          "id": "MEM-2023-002",
          "name": "Betty Ann Smith",
          "feedback": "Great event!"
        },
        {
          "id": "MEM-2023-003",
          "name": "Mary Jane Wilson",
          "feedback": "Very informative."
        }
      ]
    }
  ]
}
